{
    "AWSTemplateFormatVersion": "2010-09-09", 
    "Description": "SUZ-LAB Formation Operational Firewall", 
    "Mappings": {
        "AvailabilityZoneMap": {
            "ap-northeast-1": {
                "AzA": "ap-northeast-1a", 
                "AzB": "ap-northeast-1b", 
                "AzC": "ap-northeast-1c"
            }
        }
    }, 
    "Parameters": {
	"VpcId": {
            "Default": "vpc-xxxxxxxx",
            "Description": "VPC ID", 
            "Type": "String"
        },
	"SourceCidrIp": {
            "Default": "192.0.2.0/24",
            "Description": "Source CIDR IP", 
            "Type": "String"
        } 
    }, 
    "Resources": {
	"EC2SecurityGroupStep": {
            "Properties": {
                "GroupDescription": "op-step", 
                "VpcId": { "Ref": "VpcId" }
            }, 
            "Type": "AWS::EC2::SecurityGroup"
        },
	"EC2SecurityGroupEc2": {
            "Properties": {
                "GroupDescription": "op-ec2", 
                "VpcId": { "Ref": "VpcId" }
            }, 
            "Type": "AWS::EC2::SecurityGroup"
        },
	"EC2SecurityGroupAdminLb": {
            "Properties": {
                "GroupDescription": "op-admin-lb", 
                "VpcId": { "Ref": "VpcId" }
            }, 
            "Type": "AWS::EC2::SecurityGroup"
        },
	"EC2SecurityGroupNat": {
            "Properties": {
                "GroupDescription": "op-nat", 
                "VpcId": { "Ref": "VpcId" }
            }, 
            "Type": "AWS::EC2::SecurityGroup"
        },
	"EC2SecurityGroupAdmin": {
            "Properties": {
                "GroupDescription": "op-admin", 
                "VpcId": { "Ref": "VpcId" }
            }, 
            "Type": "AWS::EC2::SecurityGroup"
        },
	"EC2SecurityGroupDbMysql": {
            "Properties": {
                "GroupDescription": "op-db-mysql", 
                "VpcId": { "Ref": "VpcId" }
            }, 
            "Type": "AWS::EC2::SecurityGroup"
        },
        "EC2SecurityGroupDbOracle": {
            "Properties": {
                "GroupDescription": "op-db-oracle", 
                "VpcId": { "Ref": "VpcId" }
            }, 
            "Type": "AWS::EC2::SecurityGroup"
        },
        "EC2SecurityGroupCacheMemcache": {
            "Properties": {
                "GroupDescription": "op-cache-memcache", 
                "VpcId": { "Ref": "VpcId" }
            }, 
            "Type": "AWS::EC2::SecurityGroup"
        },
	"EC2SecurityGroupMaintenance": {
            "Properties": {
                "GroupDescription": "od-maintenance", 
                "VpcId": { "Ref": "VpcId" }
            }, 
            "Type": "AWS::EC2::SecurityGroup"
        },
         "EC2SecurityGroupVpc": {
            "Properties": {
                "GroupDescription": "op-vpc",
                "VpcId": { "Ref": "VpcId" }
            },
            "Type": "AWS::EC2::SecurityGroup"
        },
        "EC2SecurityGroupPublic": {
            "Properties": {
                "GroupDescription": "op-public",
                "VpcId": { "Ref": "VpcId" }
            },
            "Type": "AWS::EC2::SecurityGroup"
        },
        "EC2SecurityGroupProtected": {
            "Properties": {
                "GroupDescription": "op-protected",
                "VpcId": { "Ref": "VpcId" }
            },
            "Type": "AWS::EC2::SecurityGroup"
        },
        "EC2SecurityGroupPrivate": {
            "Properties": {
                "GroupDescription": "op-private",
                "VpcId": { "Ref": "VpcId" }
            },
            "Type": "AWS::EC2::SecurityGroup"
        },
	"EC2SecurityGroupIngressStepSshSource": {
            "Type": "AWS::EC2::SecurityGroupIngress",
            "Properties": {
                "GroupId": { "Ref": "EC2SecurityGroupStep" },
                "IpProtocol": "6",
                "FromPort": "22",
                "ToPort": "22",
		"CidrIp": { "Ref": "SourceCidrIp" }
            }
	},
	"EC2SecurityGroupEgressStepSshEc2": {
            "Type": "AWS::EC2::SecurityGroupEgress",
            "Properties": {
                "GroupId": { "Ref": "EC2SecurityGroupStep" },
                "IpProtocol": "6",
                "FromPort": "22",
                "ToPort": "22",
                "DestinationSecurityGroupId": { "Ref": "EC2SecurityGroupEc2" }
            }
        },
	"EC2SecurityGroupEgressStepNtpInternet": {
            "Type": "AWS::EC2::SecurityGroupEgress",
            "Properties": {
                "GroupId": { "Ref": "EC2SecurityGroupStep" },
                "IpProtocol": "17",
                "FromPort": "123",
                "ToPort": "123",
                "CidrIp": "0.0.0.0/0"
            }
        },
	"EC2SecurityGroupIngressEc2SshStep": {
            "Type": "AWS::EC2::SecurityGroupIngress",
            "Properties": {
                "GroupId": { "Ref": "EC2SecurityGroupEc2" },
                "IpProtocol": "6",
                "FromPort": "22",
                "ToPort": "22",
                "SourceSecurityGroupId": { "Ref": "EC2SecurityGroupStep" }
            }
	},
	"EC2SecurityGroupIngressEc2AllAdmin": {
            "Type": "AWS::EC2::SecurityGroupIngress",
            "Properties": {
                "GroupId": { "Ref": "EC2SecurityGroupEc2" },
                "IpProtocol": "-1",
                "FromPort": "-1",
                "ToPort": "-1",
                "SourceSecurityGroupId": { "Ref": "EC2SecurityGroupAdmin" }
            }
	},
	"EC2SecurityGroupEgressEc2NtpNat": {
            "Type": "AWS::EC2::SecurityGroupEgress",
            "Properties": {
                "GroupId": { "Ref": "EC2SecurityGroupEc2" },
                "IpProtocol": "17",
                "FromPort": "123",
                "ToPort": "123",
                "DestinationSecurityGroupId": { "Ref": "EC2SecurityGroupNat" }
            }
        },
	"EC2SecurityGroupEgressEc2LdapAdmin": {
            "Type": "AWS::EC2::SecurityGroupEgress",
            "Properties": {
                "GroupId": { "Ref": "EC2SecurityGroupEc2" },
                "IpProtocol": "6",
                "FromPort": "389",
                "ToPort": "389",
                "DestinationSecurityGroupId": { "Ref": "EC2SecurityGroupAdmin" }
            }
        },
	"EC2SecurityGroupIngressAdminLbHttpsSource": {
            "Type": "AWS::EC2::SecurityGroupIngress",
            "Properties": {
                "GroupId": { "Ref": "EC2SecurityGroupAdminLb" },
                "IpProtocol": "6",
                "FromPort": "443",
                "ToPort": "443",
		"CidrIp": { "Ref": "SourceCidrIp" }
            }
	},
	"EC2SecurityGroupEgressAdminLbHttpAdmin": {
            "Type": "AWS::EC2::SecurityGroupEgress",
            "Properties": {
                "GroupId": { "Ref": "EC2SecurityGroupAdminLb" },
                "IpProtocol": "6",
                "FromPort": "80",
                "ToPort": "80",
                "DestinationSecurityGroupId": { "Ref": "EC2SecurityGroupAdmin" }
            }
        },
	"EC2SecurityGroupIngressNatHttpMaintenance": {
            "Type": "AWS::EC2::SecurityGroupIngress",
            "Properties": {
                "GroupId": { "Ref": "EC2SecurityGroupNat" },
                "IpProtocol": "6",
                "FromPort": "80",
                "ToPort": "80",
                "SourceSecurityGroupId": { "Ref": "EC2SecurityGroupMaintenance" }
            }
        },
	"EC2SecurityGroupIngressNatHttpsMaintenance": {
            "Type": "AWS::EC2::SecurityGroupIngress",
            "Properties": {
                "GroupId": { "Ref": "EC2SecurityGroupNat" },
                "IpProtocol": "6",
                "FromPort": "443",
                "ToPort": "443",
                "SourceSecurityGroupId": { "Ref": "EC2SecurityGroupMaintenance" }
            }
        },
	"EC2SecurityGroupIngressNatNtpEc2": {
            "Type": "AWS::EC2::SecurityGroupIngress",
            "Properties": {
                "GroupId": { "Ref": "EC2SecurityGroupNat" },
                "IpProtocol": "17",
                "FromPort": "123",
                "ToPort": "123",
                "SourceSecurityGroupId": { "Ref": "EC2SecurityGroupEc2" }
            }
        },
	"EC2SecurityGroupEgressNatAllInternet": {
            "Type": "AWS::EC2::SecurityGroupEgress",
            "Properties": {
                "GroupId": { "Ref": "EC2SecurityGroupNat" },
                "IpProtocol": "-1",
                "FromPort": "-1",
                "ToPort": "-1",
                "CidrIp": "0.0.0.0/0"
            }
        },
	"EC2SecurityGroupIngressAdminLdapEc2": {
            "Type": "AWS::EC2::SecurityGroupIngress",
            "Properties": {
                "GroupId": { "Ref": "EC2SecurityGroupAdmin" },
                "IpProtocol": "6",
                "FromPort": "389",
                "ToPort": "389",
                "SourceSecurityGroupId": { "Ref": "EC2SecurityGroupEc2" }
            }
        },
	"EC2SecurityGroupIngressAdminHttpAdminLb": {
            "Type": "AWS::EC2::SecurityGroupIngress",
            "Properties": {
                "GroupId": { "Ref": "EC2SecurityGroupAdmin" },
                "IpProtocol": "6",
                "FromPort": "80",
                "ToPort": "80",
                "SourceSecurityGroupId": { "Ref": "EC2SecurityGroupAdminLb" }
            }
        },
	"EC2SecurityGroupEgressAdminAllEc2": {
            "Type": "AWS::EC2::SecurityGroupEgress",
            "Properties": {
                "GroupId": { "Ref": "EC2SecurityGroupAdmin" },
                "IpProtocol": "-1",
                "FromPort": "-1",
                "ToPort": "-1",
                "DestinationSecurityGroupId": { "Ref": "EC2SecurityGroupEc2" }
            }
        },
	"EC2SecurityGroupEgressAdminMysqlDbMysql": {
            "Type": "AWS::EC2::SecurityGroupEgress",
            "Properties": {
                "GroupId": { "Ref": "EC2SecurityGroupAdmin" },
                "IpProtocol": "6",
                "FromPort": "3306",
                "ToPort": "3306",
                "DestinationSecurityGroupId": { "Ref": "EC2SecurityGroupDbMysql" }
            }
        },
	"EC2SecurityGroupEgressAdminOracleDbOracle": {
            "Type": "AWS::EC2::SecurityGroupEgress",
            "Properties": {
                "GroupId": { "Ref": "EC2SecurityGroupAdmin" },
                "IpProtocol": "6",
                "FromPort": "1521",
                "ToPort": "1521",
                "DestinationSecurityGroupId": { "Ref": "EC2SecurityGroupDbOracle" }
            }
        },
	"EC2SecurityGroupIngressDbMysqlMysqlAdmin": {
            "Type": "AWS::EC2::SecurityGroupIngress",
            "Properties": {
                "GroupId": { "Ref": "EC2SecurityGroupDbMysql" },
                "IpProtocol": "6",
                "FromPort": "3306",
                "ToPort": "3306",
                "SourceSecurityGroupId": { "Ref": "EC2SecurityGroupAdmin" }
            }
        },
	"EC2SecurityGroupEgressDbMysqlMysqlDbMysql": {
            "Type": "AWS::EC2::SecurityGroupEgress",
            "Properties": {
                "GroupId": { "Ref": "EC2SecurityGroupDbMysql" },
                "IpProtocol": "6",
                "FromPort": "3306",
                "ToPort": "3306",
                "DestinationSecurityGroupId": { "Ref": "EC2SecurityGroupDbMysql" }
            }
        },
	"EC2SecurityGroupIngressDbOracleOracleAdmin": {
            "Type": "AWS::EC2::SecurityGroupIngress",
            "Properties": {
                "GroupId": { "Ref": "EC2SecurityGroupDbOracle" },
                "IpProtocol": "6",
                "FromPort": "1521",
                "ToPort": "1521",
                "SourceSecurityGroupId": { "Ref": "EC2SecurityGroupAdmin" }
            }
        },
	"EC2SecurityGroupEgressDbOracleOracleDbOracle": {
            "Type": "AWS::EC2::SecurityGroupEgress",
            "Properties": {
                "GroupId": { "Ref": "EC2SecurityGroupDbOracle" },
                "IpProtocol": "6",
                "FromPort": "1521",
                "ToPort": "1521",
                "DestinationSecurityGroupId": { "Ref": "EC2SecurityGroupDbOracle" }
            }
        },	
	"EC2SecurityGroupIngressCacheMemcacheMemcacheAdmin": {
            "Type": "AWS::EC2::SecurityGroupIngress",
            "Properties": {
                "GroupId": { "Ref": "EC2SecurityGroupCacheMemcache" },
                "IpProtocol": "6",
                "FromPort": "11211",
                "ToPort": "11211",
                "SourceSecurityGroupId": { "Ref": "EC2SecurityGroupAdmin" }
            }
        },
	"EC2SecurityGroupEgressCacheMemcacheMemcacheCacheMemcache": {
            "Type": "AWS::EC2::SecurityGroupEgress",
            "Properties": {
                "GroupId": { "Ref": "EC2SecurityGroupCacheMemcache" },
                "IpProtocol": "6",
                "FromPort": "11211",
                "ToPort": "11211",
                "DestinationSecurityGroupId": { "Ref": "EC2SecurityGroupCacheMemcache" }
            }
        },	
	"EC2SecurityGroupEgressMaintenanceHttpInternet": {
            "Type": "AWS::EC2::SecurityGroupEgress",
            "Properties": {
                "GroupId": { "Ref": "EC2SecurityGroupMaintenance" },
                "IpProtocol": "6",
                "FromPort": "80",
                "ToPort": "80",
                "CidrIp": "0.0.0.0/0"
            }
        },
	"EC2SecurityGroupEgressMaintenanceHttpsInternet": {
            "Type": "AWS::EC2::SecurityGroupEgress",
            "Properties": {
                "GroupId": { "Ref": "EC2SecurityGroupMaintenance" },
                "IpProtocol": "6",
                "FromPort": "443",
                "ToPort": "443",
                "CidrIp": "0.0.0.0/0"
            }
        },
        "EC2SecurityGroupIngressVpcInternal": {
            "Type": "AWS::EC2::SecurityGroupIngress",
            "Properties": {
                "GroupId": { "Ref": "EC2SecurityGroupVpc" },
                "IpProtocol": "-1",
                "FromPort": "-1",
                "ToPort": "-1",
                "SourceSecurityGroupId": { "Ref": "EC2SecurityGroupVpc" }
            }
        },
        "EC2SecurityGroupEgressVpcInternal": {
            "Type": "AWS::EC2::SecurityGroupEgress",
            "Properties": {
                "GroupId": { "Ref": "EC2SecurityGroupVpc" },
                "IpProtocol": "-1",
                "FromPort": "-1",
                "ToPort": "-1",
                "DestinationSecurityGroupId": { "Ref": "EC2SecurityGroupVpc" }
            }   
        },
        "EC2SecurityGroupIngressPublicInternal": {
            "Type": "AWS::EC2::SecurityGroupIngress",
            "Properties": {
                "GroupId": { "Ref": "EC2SecurityGroupPublic" },
                "IpProtocol": "-1",
                "FromPort": "-1",
                "ToPort": "-1",
                "SourceSecurityGroupId": { "Ref": "EC2SecurityGroupPublic" }
            }   
        },  
        "EC2SecurityGroupEgressPublicInternal": {
            "Type": "AWS::EC2::SecurityGroupEgress",
            "Properties": {
                "GroupId": { "Ref": "EC2SecurityGroupPublic" },
                "IpProtocol": "-1",
                "FromPort": "-1",
                "ToPort": "-1",
                "DestinationSecurityGroupId": { "Ref": "EC2SecurityGroupPublic" }
            }        
        },       
        "EC2SecurityGroupIngressProtectedInternal": {
            "Type": "AWS::EC2::SecurityGroupIngress",
            "Properties": {
                "GroupId": { "Ref": "EC2SecurityGroupProtected" },
                "IpProtocol": "-1",
                "FromPort": "-1",
                "ToPort": "-1",
                "SourceSecurityGroupId": { "Ref": "EC2SecurityGroupProtected" }
            }   
        },  
        "EC2SecurityGroupEgressProtectedInternal": {
            "Type": "AWS::EC2::SecurityGroupEgress",
            "Properties": {
                "GroupId": { "Ref": "EC2SecurityGroupProtected" },
                "IpProtocol": "-1",
                "FromPort": "-1",
                "ToPort": "-1",
                "DestinationSecurityGroupId": { "Ref": "EC2SecurityGroupProtected" }
            }        
        },       
        "EC2SecurityGroupIngressPrivateInternal": {
            "Type": "AWS::EC2::SecurityGroupIngress",
            "Properties": {
                "GroupId": { "Ref": "EC2SecurityGroupPrivate" },
                "IpProtocol": "-1",
                "FromPort": "-1",
                "ToPort": "-1",
                "SourceSecurityGroupId": { "Ref": "EC2SecurityGroupPrivate" }
            }   
        },  
        "EC2SecurityGroupEgressPrivateInternal": {
            "Type": "AWS::EC2::SecurityGroupEgress",
            "Properties": {
                "GroupId": { "Ref": "EC2SecurityGroupPrivate" },
                "IpProtocol": "-1",
                "FromPort": "-1",
                "ToPort": "-1",
                "DestinationSecurityGroupId": { "Ref": "EC2SecurityGroupPrivate" }
            }        
        }
    },
    "Outputs": {
        "GithubMarkdown": {
            "Description": "Github Markdown",
            "Value": "https://github.com/suz-lab/suz-lab-centos-ami/blob/master/share/cloudfromation/suz-lab_operational-firewall.md"
        }, 
        "GithubJson": {
            "Description": "Github JSON",
            "Value": "https://github.com/suz-lab/suz-lab-centos-ami/blob/master/share/cloudfromation/suz-lab_operational-firewall.json"
        }, 
        "S3JsonApNortheast1": {
            "Description": "S3 JSON ap-northeast-1",
            "Value": "http://ap-northeast-1.template.suz-lab.com.s3.amazonaws.com/template/suz-lab_operational-firewall/0.0.4.json"
        }, 
	"CacooImage": {
            "Description": "Cacoo Image",
            "Value": "https://cacoo.com/diagrams/XXXXXXXXXXXXXXXX-XXXXX.png"
        }, 
	"SecurityGroupIdEc2": {
            "Description": "Security Group ID EC2",
	    "Value": { "Ref": "EC2SecurityGroupEc2" }
        },
	"SecurityGroupIdStep": {
            "Description": "Security Group ID STEP",
	    "Value": { "Ref": "EC2SecurityGroupStep" }
        },
	"SecurityGroupIdNat": {
            "Description": "Security Group ID NAT",
	    "Value": { "Ref": "EC2SecurityGroupNat" }
        }
    }
}
